MANIFEST.in
README.rst
setup.cfg
setup.py
deform_bootstrap_extensions/.__init__.py.swp
deform_bootstrap_extensions/__init__.py
deform_bootstrap_extensions/__init__.pyc
deform_bootstrap_extensions.egg-info/PKG-INFO
deform_bootstrap_extensions.egg-info/SOURCES.txt
deform_bootstrap_extensions.egg-info/dependency_links.txt
deform_bootstrap_extensions.egg-info/requires.txt
deform_bootstrap_extensions.egg-info/top_level.txt
deform_bootstrap_extensions/templates/accordion_form.pt
deform_bootstrap_extensions/templates/accordion_mapping.pt
deform_bootstrap_extensions/templates/chosen_optgroup.pt
deform_bootstrap_extensions/templates/dateinput.pt
deform_bootstrap_extensions/templates/datetimeinput.pt
deform_bootstrap_extensions/templates/disabledinput.pt
deform_bootstrap_extensions/templates/grid_form.pt
deform_bootstrap_extensions/templates/grid_mapping.pt
deform_bootstrap_extensions/templates/grid_mapping_item.pt
deform_bootstrap_extensions/templates/inline_mapping.pt
deform_bootstrap_extensions/templates/inline_mapping_item.pt
docs/Makefile
docs/build/doctrees/deform_bootstrap_extensions.doctree
docs/build/doctrees/environment.pickle
docs/build/doctrees/index.doctree
docs/build/doctrees/modules.doctree
docs/build/html/.buildinfo
docs/build/html/deform_bootstrap_extensions.html
docs/build/html/genindex.html
docs/build/html/index.html
docs/build/html/modules.html
docs/build/html/objects.inv
docs/build/html/py-modindex.html
docs/build/html/search.html
docs/build/html/searchindex.js
docs/build/html/_sources/deform_bootstrap_extensions.txt
docs/build/html/_sources/index.txt
docs/build/html/_sources/modules.txt
docs/build/html/_static/ajax-loader.gif
docs/build/html/_static/basic.css
docs/build/html/_static/comment-bright.png
docs/build/html/_static/comment-close.png
docs/build/html/_static/comment.png
docs/build/html/_static/default.css
docs/build/html/_static/doctools.js
docs/build/html/_static/down-pressed.png
docs/build/html/_static/down.png
docs/build/html/_static/file.png
docs/build/html/_static/jquery.js
docs/build/html/_static/minus.png
docs/build/html/_static/plus.png
docs/build/html/_static/pygments.css
docs/build/html/_static/searchtools.js
docs/build/html/_static/sidebar.js
docs/build/html/_static/underscore.js
