Metadata-Version: 1.1
Name: deform-bootstrap-extensions
Version: 0.1a
Summary: Usefull tools for making grid/accordion layouted forms
Home-page: https://github.com/majerteam/deform_bootstrap_extensions
Author: Gaston Tjebbes - Majerti
Author-email: tech@majerti.fr
License: GPLv3
Platform: UNKNOWN
Classifier: Environment :: Web Environment
Classifier: Intended Audience :: Developers
Classifier: License :: OSI Approved :: GNU General Public License v3 (GPLv3)
Classifier: Operating System :: OS Independent
Classifier: Programming Language :: Python
Classifier: Programming Language :: Python :: 2.7
Classifier: Topic :: Internet :: WWW/HTTP
Classifier: Topic :: Internet :: WWW/HTTP :: Dynamic Content
